README.md
setup.cfg
setup.py
pyturf.egg-info/PKG-INFO
pyturf.egg-info/SOURCES.txt
pyturf.egg-info/dependency_links.txt
pyturf.egg-info/requires.txt
pyturf.egg-info/top_level.txt
turf/__init__.py
turf/version.py
turf/along/__init__.py
turf/along/_along.py
turf/area/__init__.py
turf/area/_area.py
turf/bbox/__init__.py
turf/bbox/_bbox.py
turf/bbox_polygon/__init__.py
turf/bbox_polygon/_bbox_polygon.py
turf/bearing/__init__.py
turf/bearing/_bearing.py
turf/boolean_disjoint/__init__.py
turf/boolean_disjoint/_boolean_disjoint.py
turf/boolean_intersects/__init__.py
turf/boolean_intersects/_boolean_intersects.py
turf/boolean_point_in_polygon/__init__.py
turf/boolean_point_in_polygon/_boolean_point_in_polygon.py
turf/boolean_point_on_line/__init__.py
turf/boolean_point_on_line/_boolean_point_on_line.py
turf/boolean_within/__init__.py
turf/boolean_within/_boolean_within.py
turf/center/__init__.py
turf/center/_center.py
turf/centroid/__init__.py
turf/centroid/_centroid.py
turf/destination/__init__.py
turf/destination/_destination.py
turf/distance/__init__.py
turf/distance/_distance.py
turf/envelope/__init__.py
turf/envelope/_envelope.py
turf/explode/__init__.py
turf/explode/_explode.py
turf/great_circle/__init__.py
turf/great_circle/_arc.py
turf/great_circle/_great_circle.py
turf/helpers/__init__.py
turf/helpers/_conversions.py
turf/helpers/_features.py
turf/helpers/_units.py
turf/hex_grid/__init__.py
turf/hex_grid/_hex_grid.py
turf/invariant/__init__.py
turf/invariant/_invariant.py
turf/length/__init__.py
turf/length/_length.py
turf/line_intersect/__init__.py
turf/line_intersect/_line_intersect.py
turf/midpoint/__init__.py
turf/midpoint/_midpoint.py
turf/nearest_point/__init__.py
turf/nearest_point/_nearest_point.py
turf/point_grid/__init__.py
turf/point_grid/_point_grid.py
turf/point_on_feature/__init__.py
turf/point_on_feature/_point_on_feature.py
turf/point_to_line_distance/__init__.py
turf/point_to_line_distance/_point_to_line_distance.py
turf/polygon_tangents/__init__.py
turf/polygon_tangents/_polygon_tangents.py
turf/polygon_to_line/__init__.py
turf/polygon_to_line/_polygon_to_line.py
