Metadata-Version: 2.1
Name: pyturf
Version: 0.6.0
Summary: Python geospatial library
Home-page: https://github.com/pyturf/pyturf
Author: Diogo Matos Chaves, Steffen Häußler
Author-email: di.matoschaves@gmail.com
License: MIT license
Keywords: geospatial,geo
Platform: UNKNOWN
Classifier: Programming Language :: Python :: 3
Classifier: License :: OSI Approved :: MIT License
Classifier: Operating System :: OS Independent
Requires-Python: >=3.5
